JiyuRYuyanDeKeyanXinxiFenxiYuFuwuFix1/README.md
JiyuRYuyanDeKeyanXinxiFenxiYuFuwuFix1/__init__.py
JiyuRYuyanDeKeyanXinxiFenxiYuFuwuFix1/__main__.py
JiyuRYuyanDeKeyanXinxiFenxiYuFuwuFix1/file.epub
JiyuRYuyanDeKeyanXinxiFenxiYuFuwuFix1/index.html
JiyuRYuyanDeKeyanXinxiFenxiYuFuwuFix1/css/__init__.py
JiyuRYuyanDeKeyanXinxiFenxiYuFuwuFix1/css/annotations.css
JiyuRYuyanDeKeyanXinxiFenxiYuFuwuFix1/css/main.css
JiyuRYuyanDeKeyanXinxiFenxiYuFuwuFix1/css/normalize.css
JiyuRYuyanDeKeyanXinxiFenxiYuFuwuFix1/css/popup.css
JiyuRYuyanDeKeyanXinxiFenxiYuFuwuFix1/font/__init__.py
JiyuRYuyanDeKeyanXinxiFenxiYuFuwuFix1/font/fontello.eot
JiyuRYuyanDeKeyanXinxiFenxiYuFuwuFix1/font/fontello.svg
JiyuRYuyanDeKeyanXinxiFenxiYuFuwuFix1/font/fontello.ttf
JiyuRYuyanDeKeyanXinxiFenxiYuFuwuFix1/font/fontello.woff
JiyuRYuyanDeKeyanXinxiFenxiYuFuwuFix1/img/__init__.py
JiyuRYuyanDeKeyanXinxiFenxiYuFuwuFix1/img/annotator-glyph-sprite.png
JiyuRYuyanDeKeyanXinxiFenxiYuFuwuFix1/img/annotator-icon-sprite.png
JiyuRYuyanDeKeyanXinxiFenxiYuFuwuFix1/img/apple-touch-icon.png
JiyuRYuyanDeKeyanXinxiFenxiYuFuwuFix1/img/cancelfullscreen.png
JiyuRYuyanDeKeyanXinxiFenxiYuFuwuFix1/img/close.png
JiyuRYuyanDeKeyanXinxiFenxiYuFuwuFix1/img/fullscreen.png
JiyuRYuyanDeKeyanXinxiFenxiYuFuwuFix1/img/loader.gif
JiyuRYuyanDeKeyanXinxiFenxiYuFuwuFix1/img/menu-icon.png
JiyuRYuyanDeKeyanXinxiFenxiYuFuwuFix1/img/save.png
JiyuRYuyanDeKeyanXinxiFenxiYuFuwuFix1/img/saved.png
JiyuRYuyanDeKeyanXinxiFenxiYuFuwuFix1/img/settings-s.png
JiyuRYuyanDeKeyanXinxiFenxiYuFuwuFix1/img/settings.png
JiyuRYuyanDeKeyanXinxiFenxiYuFuwuFix1/img/star.png
JiyuRYuyanDeKeyanXinxiFenxiYuFuwuFix1/js/__init__.py
JiyuRYuyanDeKeyanXinxiFenxiYuFuwuFix1/js/epub.js
JiyuRYuyanDeKeyanXinxiFenxiYuFuwuFix1/js/epub.min.js
JiyuRYuyanDeKeyanXinxiFenxiYuFuwuFix1/js/epub.min.map
JiyuRYuyanDeKeyanXinxiFenxiYuFuwuFix1/js/hooks.min.js
JiyuRYuyanDeKeyanXinxiFenxiYuFuwuFix1/js/hooks.min.map
JiyuRYuyanDeKeyanXinxiFenxiYuFuwuFix1/js/reader.js
jiyu_r_yuyan_de_keyan_xinxi_fenxi_yu_fuwu_fix1-2025.3.25.0.dist-info/METADATA
jiyu_r_yuyan_de_keyan_xinxi_fenxi_yu_fuwu_fix1-2025.3.25.0.dist-info/WHEEL
jiyu_r_yuyan_de_keyan_xinxi_fenxi_yu_fuwu_fix1-2025.3.25.0.dist-info/entry_points.txt
jiyu_r_yuyan_de_keyan_xinxi_fenxi_yu_fuwu_fix1-2025.3.25.0.dist-info/top_level.txt
jiyu_r_yuyan_de_keyan_xinxi_fenxi_yu_fuwu_fix1-2025.3.25.0.dist-info/RECORD
